llmark/__init__.py
llmark/__main__.py
llmark/_c_extension.pyi
llmark/cli/__init__.py
llmark/cli/main.py
llmark/context.py
llmark/prompt_template.j2
llmark/py.typed
llmark-0.0.1.dist-info/LICENSE
llmark-0.0.1.dist-info/METADATA
llmark-0.0.1.dist-info/WHEEL
llmark-0.0.1.dist-info/entry_points.txt
llmark-0.0.1.dist-info/RECORD
